cloneit/__init__.py
cloneit/_version.py
cloneit/core.py
cloneit/exceptions.py
cloneit-0.1.0.dist-info/licenses/LICENSE
cloneit-0.1.0.dist-info/METADATA
cloneit-0.1.0.dist-info/WHEEL
cloneit-0.1.0.dist-info/top_level.txt
cloneit-0.1.0.dist-info/RECORD
