Metadata-Version: 2.4
Name: cloneit
Version: 0.1.0
Summary: A lightweight Python package inspired by RPGLE LIKE keyword for cloning field templates
Author-email: Neeraj <neeraj@example.com>
License-Expression: MIT
Project-URL: Homepage, https://github.com/neeraj/cloneit
Project-URL: Repository, https://github.com/neeraj/cloneit
Project-URL: Documentation, https://github.com/neeraj/cloneit#readme
Project-URL: Bug Reports, https://github.com/neeraj/cloneit/issues
Keywords: field,template,clone,rpgle,like,data,model,schema,django,pydantic,marshmallow,validation,boilerplate
Classifier: Development Status :: 4 - Beta
Classifier: Intended Audience :: Developers
Classifier: Operating System :: OS Independent
Classifier: Programming Language :: Python :: 3
Classifier: Programming Language :: Python :: 3.6
Classifier: Programming Language :: Python :: 3.7
Classifier: Programming Language :: Python :: 3.8
Classifier: Programming Language :: Python :: 3.9
Classifier: Programming Language :: Python :: 3.10
Classifier: Programming Language :: Python :: 3.11
Classifier: Programming Language :: Python :: 3.12
Classifier: Topic :: Software Development :: Libraries :: Python Modules
Classifier: Topic :: Software Development :: Code Generators
Classifier: Topic :: Database
Classifier: Topic :: Internet :: WWW/HTTP :: Dynamic Content
Requires-Python: >=3.6
License-File: LICENSE
Provides-Extra: dev
Requires-Dist: pytest>=6.0; extra == "dev"
Requires-Dist: pytest-cov>=2.0; extra == "dev"
Requires-Dist: black>=21.0; extra == "dev"
Requires-Dist: flake8>=3.8; extra == "dev"
Requires-Dist: mypy>=0.800; extra == "dev"
Requires-Dist: twine>=3.0; extra == "dev"
Dynamic: license-file
